agents/__init__.py
agents/_config.py
agents/_debug.py
agents/_run_impl.py
agents/_utils.py
agents/agent.py
agents/agent_output.py
agents/computer.py
agents/exceptions.py
agents/function_schema.py
agents/guardrail.py
agents/handoffs.py
agents/items.py
agents/lifecycle.py
agents/logger.py
agents/model_settings.py
agents/result.py
agents/run.py
agents/run_context.py
agents/stream_events.py
agents/strict_schema.py
agents/tool.py
agents/tool_enhanced.py
agents/usage.py
agents/version.py
agents/extensions/__init__.py
agents/extensions/handoff_filters.py
agents/extensions/handoff_prompt.py
agents/extensions/cli/__init__.py
agents/extensions/cli/cli_agent.py
agents/extensions/marketplace/__init__.py
agents/extensions/marketplace/marketplace.py
agents/extensions/tee/__init__.py
agents/extensions/tee/tee.py
agents/extensions/web3/__init__.py
agents/extensions/web3/wallet.py
agents/extensions/web3/web3_agent.py
agents/extensions/web3/web3_network.py
agents/memory/__init__.py
agents/memory/memory.py
agents/memory/retriever.py
agents/memory/store.py
agents/memory/types.py
agents/models/__init__.py
agents/models/_openai_shared.py
agents/models/fake_id.py
agents/models/hanzo_node_provider.py
agents/models/interface.py
agents/models/openai_chatcompletions.py
agents/models/openai_provider.py
agents/models/openai_responses.py
agents/network/__init__.py
agents/network/network.py
agents/network/node.py
agents/network/router.py
agents/orchestration/__init__.py
agents/orchestration/executor.py
agents/orchestration/orchestrator.py
agents/orchestration/ui_stream.py
agents/orchestration/workflow.py
agents/state/__init__.py
agents/state/namespace.py
agents/state/serializer.py
agents/state/store.py
agents/tracing/__init__.py
agents/tracing/create.py
agents/tracing/logger.py
agents/tracing/processor_interface.py
agents/tracing/processors.py
agents/tracing/scope.py
agents/tracing/setup.py
agents/tracing/span_data.py
agents/tracing/spans.py
agents/tracing/traces.py
agents/tracing/util.py
hanzo_agent-0.1.0.dist-info/METADATA
hanzo_agent-0.1.0.dist-info/WHEEL
hanzo_agent-0.1.0.dist-info/licenses/LICENSE
hanzo_agent-0.1.0.dist-info/RECORD
