Metadata-Version: 2.4
Name: hanzo-agent
Version: 0.1.0
Summary: Hanzo AI Agent SDK - Build agentic AI apps with a lightweight, production-ready SDK
Project-URL: Homepage, https://github.com/hanzoai/agent
Project-URL: Repository, https://github.com/hanzoai/agent
Author-email: Hanzo AI <support@hanzo.ai>
License-Expression: MIT
License-File: LICENSE
Classifier: Intended Audience :: Developers
Classifier: License :: OSI Approved :: MIT License
Classifier: Operating System :: OS Independent
Classifier: Programming Language :: Python :: 3
Classifier: Programming Language :: Python :: 3.9
Classifier: Programming Language :: Python :: 3.10
Classifier: Programming Language :: Python :: 3.11
Classifier: Programming Language :: Python :: 3.12
Classifier: Topic :: Software Development :: Libraries :: Python Modules
Classifier: Typing :: Typed
Requires-Python: >=3.9
Requires-Dist: griffe<2,>=1.5.6
Requires-Dist: openai>=1.66.2
Requires-Dist: pydantic<3,>=2.10
Requires-Dist: requests<3,>=2.0
Requires-Dist: types-requests<3,>=2.0
Requires-Dist: typing-extensions<5,>=4.12.2
Provides-Extra: cli
Requires-Dist: click<9,>=8.1.0; extra == 'cli'
Requires-Dist: rich<14,>=13.0.0; extra == 'cli'
Provides-Extra: full
Requires-Dist: hanzoai[cli,marketplace,tee,web3]; extra == 'full'
Provides-Extra: marketplace
Requires-Dist: aiohttp<4,>=3.9.0; extra == 'marketplace'
Requires-Dist: redis<6,>=5.0.0; extra == 'marketplace'
Provides-Extra: tee
Requires-Dist: cryptography<50,>=41.0.0; extra == 'tee'
Provides-Extra: web3
Requires-Dist: eth-account<1,>=0.10.0; extra == 'web3'
Requires-Dist: eth-utils<5,>=2.0.0; extra == 'web3'
Requires-Dist: web3<7,>=6.0.0; extra == 'web3'
